<?xml version="1.0" encoding="utf-8"?>
<VärdepappersfondInnehav xmlns="http://schemas.fi.se/publika/vardepappersfonder/20200331">
  <Rapportinformation>
    <Kvartalsslut>2024-12-31</Kvartalsslut>
  </Rapportinformation>
  <Bolagsinformation>
    <Fondbolag_namn>Cliens Kapitalförvaltning AB</Fondbolag_namn>
    <Fondbolag_institutnummer>58193</Fondbolag_institutnummer>
    <Fondbolag_LEI-kod>5493001XOIKH56D1VB49</Fondbolag_LEI-kod>
  </Bolagsinformation>
  <Fondinformation>
    <Fond_institutnummer>63960</Fond_institutnummer>
    <Fond_ISIN-kod>SE0016830749</Fond_ISIN-kod>
    <Fond_namn>Cliens Global Småbolag</Fond_namn>
    <Förvaltningsavgift>
      <MedAndelsklasser>
        <Förvaltningsavgift>
          <Andelsklass_namn>CLIENS GLOBAL SMÅBOLAG A</Andelsklass_namn>
          <Förvaltningsavgift_Typ>
            <Förvaltningsavgift_fast>1.35</Förvaltningsavgift_fast>
            <Förvaltningsavgift_Prestationsbaserad>
              <Avkastningströskel>MSCI World Small Cap TR Net Index</Avkastningströskel>
              <ProcentuelltUttag>10</ProcentuelltUttag>
            </Förvaltningsavgift_Prestationsbaserad>
          </Förvaltningsavgift_Typ>
        </Förvaltningsavgift>
        <Förvaltningsavgift>
          <Andelsklass_namn>CLIENS GLOBAL SMÅBOLAG B</Andelsklass_namn>
          <Förvaltningsavgift_Typ>
            <Förvaltningsavgift_fast>0.65</Förvaltningsavgift_fast>
            <Förvaltningsavgift_Prestationsbaserad>
              <Avkastningströskel>MSCI World Small Cap TR Net Index</Avkastningströskel>
              <ProcentuelltUttag>10</ProcentuelltUttag>
            </Förvaltningsavgift_Prestationsbaserad>
          </Förvaltningsavgift_Typ>
        </Förvaltningsavgift>
      </MedAndelsklasser>
    </Förvaltningsavgift>
    <Fondförmögenhet>944209992</Fondförmögenhet>
    <Likvida_medel>68789067</Likvida_medel>
    <Övriga_tillgångar_och_skulder>-1195388</Övriga_tillgångar_och_skulder>
    <Aktiv_risk>4.23</Aktiv_risk>
    <Standardavvikelse_24_månader>16.81</Standardavvikelse_24_månader>
    <Jämförelseindex>
      <Jämförelseindex>M1WOSC</Jämförelseindex>
    </Jämförelseindex>
    <FinansiellaInstrument>
      <FinansielltInstrument>
        <Tillgångsslag_enligt_LVF_5_kap>ÖverlåtbartVärdepapper</Tillgångsslag_enligt_LVF_5_kap>
        <Instrumentnamn>LABORATORIOS FARMACE</Instrumentnamn>
        <ISIN-kod_instrument>ES0157261019</ISIN-kod_instrument>
        <Landkod_Emittent>ES</Landkod_Emittent>
        <Valuta>EUR</Valuta>
        <Antal>20400</Antal>
        <Nominellt_belopp />
        <Kurs_som_använts_vid_värdering_av_instrumentet>62.95</Kurs_som_använts_vid_värdering_av_instrumentet>
        <Valutakurs_instrument>11.4637</Valutakurs_instrument>
        <Marknadsvärde_instrument>14721454.27</Marknadsvärde_instrument>
        <Andel_av_fondförmögenhet_instrument>1.56</Andel_av_fondförmögenhet_instrument>
        <Bransch>
          <Branschkod_instrument>35</Branschkod_instrument>
          <Bransch_namn_instrument>Hälsovård</Bransch_namn_instrument>
        </Bransch>
      </FinansielltInstrument>
      <FinansielltInstrument>
        <Tillgångsslag_enligt_LVF_5_kap>ÖverlåtbartVärdepapper</Tillgångsslag_enligt_LVF_5_kap>
        <Instrumentnamn>KINSALE CAP. GROUP</Instrumentnamn>
        <ISIN-kod_instrument>US49714P1084</ISIN-kod_instrument>
        <Landkod_Emittent>US</Landkod_Emittent>
        <Valuta>USD</Valuta>
        <Antal>5000</Antal>
        <Nominellt_belopp />
        <Kurs_som_använts_vid_värdering_av_instrumentet>465.13</Kurs_som_använts_vid_värdering_av_instrumentet>
        <Valutakurs_instrument>11.045</Valutakurs_instrument>
        <Marknadsvärde_instrument>25686804.25</Marknadsvärde_instrument>
        <Andel_av_fondförmögenhet_instrument>2.72</Andel_av_fondförmögenhet_instrument>
        <Bransch>
          <Branschkod_instrument>40</Branschkod_instrument>
          <Bransch_namn_instrument>Finans</Bransch_namn_instrument>
        </Bransch>
      </FinansielltInstrument>
      <FinansielltInstrument>
        <Tillgångsslag_enligt_LVF_5_kap>ÖverlåtbartVärdepapper</Tillgångsslag_enligt_LVF_5_kap>
        <Instrumentnamn>PALOMAR HOLDINGS INC</Instrumentnamn>
        <ISIN-kod_instrument>US69753M1053</ISIN-kod_instrument>
        <Landkod_Emittent>US</Landkod_Emittent>
        <Valuta>USD</Valuta>
        <Antal>20000</Antal>
        <Nominellt_belopp />
        <Kurs_som_använts_vid_värdering_av_instrumentet>105.59</Kurs_som_använts_vid_värdering_av_instrumentet>
        <Valutakurs_instrument>11.045</Valutakurs_instrument>
        <Marknadsvärde_instrument>23324831</Marknadsvärde_instrument>
        <Andel_av_fondförmögenhet_instrument>2.47</Andel_av_fondförmögenhet_instrument>
        <Bransch>
          <Branschkod_instrument>40</Branschkod_instrument>
          <Bransch_namn_instrument>Finans</Bransch_namn_instrument>
        </Bransch>
      </FinansielltInstrument>
      <FinansielltInstrument>
        <Tillgångsslag_enligt_LVF_5_kap>ÖverlåtbartVärdepapper</Tillgångsslag_enligt_LVF_5_kap>
        <Instrumentnamn>OLD REPUBLIC INTL</Instrumentnamn>
        <ISIN-kod_instrument>US6802231042</ISIN-kod_instrument>
        <Landkod_Emittent>US</Landkod_Emittent>
        <Valuta>USD</Valuta>
        <Antal>53000</Antal>
        <Nominellt_belopp />
        <Kurs_som_använts_vid_värdering_av_instrumentet>36.19</Kurs_som_använts_vid_värdering_av_instrumentet>
        <Valutakurs_instrument>11.045</Valutakurs_instrument>
        <Marknadsvärde_instrument>21185083.15</Marknadsvärde_instrument>
        <Andel_av_fondförmögenhet_instrument>2.24</Andel_av_fondförmögenhet_instrument>
        <Bransch>
          <Branschkod_instrument>40</Branschkod_instrument>
          <Bransch_namn_instrument>Finans</Bransch_namn_instrument>
        </Bransch>
      </FinansielltInstrument>
      <FinansielltInstrument>
        <Tillgångsslag_enligt_LVF_5_kap>ÖverlåtbartVärdepapper</Tillgångsslag_enligt_LVF_5_kap>
        <Instrumentnamn>INSTALLED BUILD PROD</Instrumentnamn>
        <ISIN-kod_instrument>US45780R1014</ISIN-kod_instrument>
        <Landkod_Emittent>US</Landkod_Emittent>
        <Valuta>USD</Valuta>
        <Antal>7450</Antal>
        <Nominellt_belopp />
        <Kurs_som_använts_vid_värdering_av_instrumentet>175.25</Kurs_som_använts_vid_värdering_av_instrumentet>
        <Valutakurs_instrument>11.045</Valutakurs_instrument>
        <Marknadsvärde_instrument>14420490.06</Marknadsvärde_instrument>
        <Andel_av_fondförmögenhet_instrument>1.53</Andel_av_fondförmögenhet_instrument>
        <Bransch>
          <Branschkod_instrument>25</Branschkod_instrument>
          <Bransch_namn_instrument>Sällanköpvaror och tjänster</Bransch_namn_instrument>
        </Bransch>
      </FinansielltInstrument>
      <FinansielltInstrument>
        <Tillgångsslag_enligt_LVF_5_kap>ÖverlåtbartVärdepapper</Tillgångsslag_enligt_LVF_5_kap>
        <Instrumentnamn>IMCD NV</Instrumentnamn>
        <ISIN-kod_instrument>NL0010801007</ISIN-kod_instrument>
        <Landkod_Emittent>NL</Landkod_Emittent>
        <Valuta>EUR</Valuta>
        <Antal>21000</Antal>
        <Nominellt_belopp />
        <Kurs_som_använts_vid_värdering_av_instrumentet>143.5</Kurs_som_använts_vid_värdering_av_instrumentet>
        <Valutakurs_instrument>11.4637</Valutakurs_instrument>
        <Marknadsvärde_instrument>34545859.95</Marknadsvärde_instrument>
        <Andel_av_fondförmögenhet_instrument>3.66</Andel_av_fondförmögenhet_instrument>
        <Bransch>
          <Branschkod_instrument>20</Branschkod_instrument>
          <Bransch_namn_instrument>Industrivaror och tjänster</Bransch_namn_instrument>
        </Bransch>
      </FinansielltInstrument>
      <FinansielltInstrument>
        <Tillgångsslag_enligt_LVF_5_kap>ÖverlåtbartVärdepapper</Tillgångsslag_enligt_LVF_5_kap>
        <Instrumentnamn>JTC PLC</Instrumentnamn>
        <ISIN-kod_instrument>JE00BF4X3P53</ISIN-kod_instrument>
        <Landkod_Emittent>JE</Landkod_Emittent>
        <Valuta>GBP</Valuta>
        <Antal>100647</Antal>
        <Nominellt_belopp />
        <Kurs_som_använts_vid_värdering_av_instrumentet>9.84</Kurs_som_använts_vid_värdering_av_instrumentet>
        <Valutakurs_instrument>13.8199</Valutakurs_instrument>
        <Marknadsvärde_instrument>13686765.72</Marknadsvärde_instrument>
        <Andel_av_fondförmögenhet_instrument>1.45</Andel_av_fondförmögenhet_instrument>
        <Bransch>
          <Branschkod_instrument>40</Branschkod_instrument>
          <Bransch_namn_instrument>Finans</Bransch_namn_instrument>
        </Bransch>
      </FinansielltInstrument>
      <FinansielltInstrument>
        <Tillgångsslag_enligt_LVF_5_kap>ÖverlåtbartVärdepapper</Tillgångsslag_enligt_LVF_5_kap>
        <Instrumentnamn>JANUS INTERNATIONAL</Instrumentnamn>
        <ISIN-kod_instrument>US47103N1063</ISIN-kod_instrument>
        <Landkod_Emittent>US</Landkod_Emittent>
        <Valuta>USD</Valuta>
        <Antal>130500</Antal>
        <Nominellt_belopp />
        <Kurs_som_använts_vid_värdering_av_instrumentet>7.35</Kurs_som_använts_vid_värdering_av_instrumentet>
        <Valutakurs_instrument>11.045</Valutakurs_instrument>
        <Marknadsvärde_instrument>10594087.88</Marknadsvärde_instrument>
        <Andel_av_fondförmögenhet_instrument>1.12</Andel_av_fondförmögenhet_instrument>
        <Bransch>
          <Branschkod_instrument>20</Branschkod_instrument>
          <Bransch_namn_instrument>Industrivaror och tjänster</Bransch_namn_instrument>
        </Bransch>
      </FinansielltInstrument>
      <FinansielltInstrument>
        <Tillgångsslag_enligt_LVF_5_kap>ÖverlåtbartVärdepapper</Tillgångsslag_enligt_LVF_5_kap>
        <Instrumentnamn>PAYLOCITY HOLD</Instrumentnamn>
        <ISIN-kod_instrument>US70438V1061</ISIN-kod_instrument>
        <Landkod_Emittent>US</Landkod_Emittent>
        <Valuta>USD</Valuta>
        <Antal>6000</Antal>
        <Nominellt_belopp />
        <Kurs_som_använts_vid_värdering_av_instrumentet>199.47</Kurs_som_använts_vid_värdering_av_instrumentet>
        <Valutakurs_instrument>11.045</Valutakurs_instrument>
        <Marknadsvärde_instrument>13218876.9</Marknadsvärde_instrument>
        <Andel_av_fondförmögenhet_instrument>1.4</Andel_av_fondförmögenhet_instrument>
        <Bransch>
          <Branschkod_instrument>20</Branschkod_instrument>
          <Bransch_namn_instrument>Industrivaror och tjänster</Bransch_namn_instrument>
        </Bransch>
      </FinansielltInstrument>
      <FinansielltInstrument>
        <Tillgångsslag_enligt_LVF_5_kap>ÖverlåtbartVärdepapper</Tillgångsslag_enligt_LVF_5_kap>
        <Instrumentnamn>VERRA MOBILITY CORP</Instrumentnamn>
        <ISIN-kod_instrument>US92511U1025</ISIN-kod_instrument>
        <Landkod_Emittent>US</Landkod_Emittent>
        <Valuta>USD</Valuta>
        <Antal>111800</Antal>
        <Nominellt_belopp />
        <Kurs_som_använts_vid_värdering_av_instrumentet>24.18</Kurs_som_använts_vid_värdering_av_instrumentet>
        <Valutakurs_instrument>11.045</Valutakurs_instrument>
        <Marknadsvärde_instrument>29858213.58</Marknadsvärde_instrument>
        <Andel_av_fondförmögenhet_instrument>3.16</Andel_av_fondförmögenhet_instrument>
        <Bransch>
          <Branschkod_instrument>20</Branschkod_instrument>
          <Bransch_namn_instrument>Industrivaror och tjänster</Bransch_namn_instrument>
        </Bransch>
      </FinansielltInstrument>
      <FinansielltInstrument>
        <Tillgångsslag_enligt_LVF_5_kap>ÖverlåtbartVärdepapper</Tillgångsslag_enligt_LVF_5_kap>
        <Instrumentnamn>SPIE SA</Instrumentnamn>
        <ISIN-kod_instrument>FR0012757854</ISIN-kod_instrument>
        <Landkod_Emittent>FR</Landkod_Emittent>
        <Valuta>EUR</Valuta>
        <Antal>95200</Antal>
        <Nominellt_belopp />
        <Kurs_som_använts_vid_värdering_av_instrumentet>30.04</Kurs_som_använts_vid_värdering_av_instrumentet>
        <Valutakurs_instrument>11.4637</Valutakurs_instrument>
        <Marknadsvärde_instrument>32783980.97</Marknadsvärde_instrument>
        <Andel_av_fondförmögenhet_instrument>3.47</Andel_av_fondförmögenhet_instrument>
        <Bransch>
          <Branschkod_instrument>20</Branschkod_instrument>
          <Bransch_namn_instrument>Industrivaror och tjänster</Bransch_namn_instrument>
        </Bransch>
      </FinansielltInstrument>
      <FinansielltInstrument>
        <Tillgångsslag_enligt_LVF_5_kap>ÖverlåtbartVärdepapper</Tillgångsslag_enligt_LVF_5_kap>
        <Instrumentnamn>WILLSCOT HOLD CORP</Instrumentnamn>
        <ISIN-kod_instrument>US9713781048</ISIN-kod_instrument>
        <Landkod_Emittent>US</Landkod_Emittent>
        <Valuta>USD</Valuta>
        <Antal>59000</Antal>
        <Nominellt_belopp />
        <Kurs_som_använts_vid_värdering_av_instrumentet>33.45</Kurs_som_använts_vid_värdering_av_instrumentet>
        <Valutakurs_instrument>11.045</Valutakurs_instrument>
        <Marknadsvärde_instrument>21797859.75</Marknadsvärde_instrument>
        <Andel_av_fondförmögenhet_instrument>2.31</Andel_av_fondförmögenhet_instrument>
        <Bransch>
          <Branschkod_instrument>20</Branschkod_instrument>
          <Bransch_namn_instrument>Industrivaror och tjänster</Bransch_namn_instrument>
        </Bransch>
      </FinansielltInstrument>
      <FinansielltInstrument>
        <Tillgångsslag_enligt_LVF_5_kap>ÖverlåtbartVärdepapper</Tillgångsslag_enligt_LVF_5_kap>
        <Instrumentnamn>WEX INC</Instrumentnamn>
        <ISIN-kod_instrument>US96208T1043</ISIN-kod_instrument>
        <Landkod_Emittent>US</Landkod_Emittent>
        <Valuta>USD</Valuta>
        <Antal>10050</Antal>
        <Nominellt_belopp />
        <Kurs_som_använts_vid_värdering_av_instrumentet>175.32</Kurs_som_använts_vid_värdering_av_instrumentet>
        <Valutakurs_instrument>11.045</Valutakurs_instrument>
        <Marknadsvärde_instrument>19460914.47</Marknadsvärde_instrument>
        <Andel_av_fondförmögenhet_instrument>2.06</Andel_av_fondförmögenhet_instrument>
        <Bransch>
          <Branschkod_instrument>40</Branschkod_instrument>
          <Bransch_namn_instrument>Finans</Bransch_namn_instrument>
        </Bransch>
      </FinansielltInstrument>
      <FinansielltInstrument>
        <Tillgångsslag_enligt_LVF_5_kap>ÖverlåtbartVärdepapper</Tillgångsslag_enligt_LVF_5_kap>
        <Instrumentnamn>Q2 HOLDINGS</Instrumentnamn>
        <ISIN-kod_instrument>US74736L1098</ISIN-kod_instrument>
        <Landkod_Emittent>US</Landkod_Emittent>
        <Valuta>USD</Valuta>
        <Antal>25900</Antal>
        <Nominellt_belopp />
        <Kurs_som_använts_vid_värdering_av_instrumentet>100.65</Kurs_som_använts_vid_värdering_av_instrumentet>
        <Valutakurs_instrument>11.045</Valutakurs_instrument>
        <Marknadsvärde_instrument>28792492.58</Marknadsvärde_instrument>
        <Andel_av_fondförmögenhet_instrument>3.05</Andel_av_fondförmögenhet_instrument>
        <Bransch>
          <Branschkod_instrument>45</Branschkod_instrument>
          <Bransch_namn_instrument>Informationsteknologi</Bransch_namn_instrument>
        </Bransch>
      </FinansielltInstrument>
      <FinansielltInstrument>
        <Tillgångsslag_enligt_LVF_5_kap>ÖverlåtbartVärdepapper</Tillgångsslag_enligt_LVF_5_kap>
        <Instrumentnamn>PLANISWARE</Instrumentnamn>
        <ISIN-kod_instrument>FR001400PFU4</ISIN-kod_instrument>
        <Landkod_Emittent>FR</Landkod_Emittent>
        <Valuta>EUR</Valuta>
        <Antal>16705</Antal>
        <Nominellt_belopp />
        <Kurs_som_använts_vid_värdering_av_instrumentet>28.12</Kurs_som_använts_vid_värdering_av_instrumentet>
        <Valutakurs_instrument>11.4637</Valutakurs_instrument>
        <Marknadsvärde_instrument>5385011.17</Marknadsvärde_instrument>
        <Andel_av_fondförmögenhet_instrument>0.57</Andel_av_fondförmögenhet_instrument>
        <Bransch>
          <Branschkod_instrument>45</Branschkod_instrument>
          <Bransch_namn_instrument>Informationsteknologi</Bransch_namn_instrument>
        </Bransch>
      </FinansielltInstrument>
      <FinansielltInstrument>
        <Tillgångsslag_enligt_LVF_5_kap>ÖverlåtbartVärdepapper</Tillgångsslag_enligt_LVF_5_kap>
        <Instrumentnamn>SERVICE CORP INTERNA</Instrumentnamn>
        <ISIN-kod_instrument>US8175651046</ISIN-kod_instrument>
        <Landkod_Emittent>US</Landkod_Emittent>
        <Valuta>USD</Valuta>
        <Antal>23500</Antal>
        <Nominellt_belopp />
        <Kurs_som_använts_vid_värdering_av_instrumentet>79.82</Kurs_som_använts_vid_värdering_av_instrumentet>
        <Valutakurs_instrument>11.045</Valutakurs_instrument>
        <Marknadsvärde_instrument>20717879.65</Marknadsvärde_instrument>
        <Andel_av_fondförmögenhet_instrument>2.19</Andel_av_fondförmögenhet_instrument>
        <Bransch>
          <Branschkod_instrument>25</Branschkod_instrument>
          <Bransch_namn_instrument>Sällanköpvaror och tjänster</Bransch_namn_instrument>
        </Bransch>
      </FinansielltInstrument>
      <FinansielltInstrument>
        <Tillgångsslag_enligt_LVF_5_kap>ÖverlåtbartVärdepapper</Tillgångsslag_enligt_LVF_5_kap>
        <Instrumentnamn>QXO INC</Instrumentnamn>
        <ISIN-kod_instrument>US82846H4056</ISIN-kod_instrument>
        <Landkod_Emittent>US</Landkod_Emittent>
        <Valuta>USD</Valuta>
        <Antal>54705</Antal>
        <Nominellt_belopp />
        <Kurs_som_använts_vid_värdering_av_instrumentet>15.9</Kurs_som_använts_vid_värdering_av_instrumentet>
        <Valutakurs_instrument>11.045</Valutakurs_instrument>
        <Marknadsvärde_instrument>9607045.93</Marknadsvärde_instrument>
        <Andel_av_fondförmögenhet_instrument>1.02</Andel_av_fondförmögenhet_instrument>
        <Bransch>
          <Branschkod_instrument>45</Branschkod_instrument>
          <Bransch_namn_instrument>Informationsteknologi</Bransch_namn_instrument>
        </Bransch>
      </FinansielltInstrument>
      <FinansielltInstrument>
        <Tillgångsslag_enligt_LVF_5_kap>ÖverlåtbartVärdepapper</Tillgångsslag_enligt_LVF_5_kap>
        <Instrumentnamn>GXO LOGISTIC</Instrumentnamn>
        <ISIN-kod_instrument>US36262G1013</ISIN-kod_instrument>
        <Landkod_Emittent>US</Landkod_Emittent>
        <Valuta>USD</Valuta>
        <Antal>37050</Antal>
        <Nominellt_belopp />
        <Kurs_som_använts_vid_värdering_av_instrumentet>43.5</Kurs_som_använts_vid_värdering_av_instrumentet>
        <Valutakurs_instrument>11.045</Valutakurs_instrument>
        <Marknadsvärde_instrument>17800950.38</Marknadsvärde_instrument>
        <Andel_av_fondförmögenhet_instrument>1.89</Andel_av_fondförmögenhet_instrument>
        <Bransch>
          <Branschkod_instrument>20</Branschkod_instrument>
          <Bransch_namn_instrument>Industrivaror och tjänster</Bransch_namn_instrument>
        </Bransch>
      </FinansielltInstrument>
      <FinansielltInstrument>
        <Tillgångsslag_enligt_LVF_5_kap>ÖverlåtbartVärdepapper</Tillgångsslag_enligt_LVF_5_kap>
        <Instrumentnamn>CARLISLE COMPANIES</Instrumentnamn>
        <ISIN-kod_instrument>US1423391002</ISIN-kod_instrument>
        <Landkod_Emittent>US</Landkod_Emittent>
        <Valuta>USD</Valuta>
        <Antal>6700</Antal>
        <Nominellt_belopp />
        <Kurs_som_använts_vid_värdering_av_instrumentet>368.84</Kurs_som_använts_vid_värdering_av_instrumentet>
        <Valutakurs_instrument>11.045</Valutakurs_instrument>
        <Marknadsvärde_instrument>27294713.26</Marknadsvärde_instrument>
        <Andel_av_fondförmögenhet_instrument>2.89</Andel_av_fondförmögenhet_instrument>
        <Bransch>
          <Branschkod_instrument>20</Branschkod_instrument>
          <Bransch_namn_instrument>Industrivaror och tjänster</Bransch_namn_instrument>
        </Bransch>
      </FinansielltInstrument>
      <FinansielltInstrument>
        <Tillgångsslag_enligt_LVF_5_kap>ÖverlåtbartVärdepapper</Tillgångsslag_enligt_LVF_5_kap>
        <Instrumentnamn>BEAZLEY ORD</Instrumentnamn>
        <ISIN-kod_instrument>GB00BYQ0JC66</ISIN-kod_instrument>
        <Landkod_Emittent>GB</Landkod_Emittent>
        <Valuta>GBP</Valuta>
        <Antal>313000</Antal>
        <Nominellt_belopp />
        <Kurs_som_använts_vid_värdering_av_instrumentet>8.165</Kurs_som_använts_vid_värdering_av_instrumentet>
        <Valutakurs_instrument>13.8199</Valutakurs_instrument>
        <Marknadsvärde_instrument>35318758.34</Marknadsvärde_instrument>
        <Andel_av_fondförmögenhet_instrument>3.74</Andel_av_fondförmögenhet_instrument>
        <Bransch>
          <Branschkod_instrument>40</Branschkod_instrument>
          <Bransch_namn_instrument>Finans</Bransch_namn_instrument>
        </Bransch>
      </FinansielltInstrument>
      <FinansielltInstrument>
        <Tillgångsslag_enligt_LVF_5_kap>ÖverlåtbartVärdepapper</Tillgångsslag_enligt_LVF_5_kap>
        <Instrumentnamn>CLEAN HARBORS INC</Instrumentnamn>
        <ISIN-kod_instrument>US1844961078</ISIN-kod_instrument>
        <Landkod_Emittent>US</Landkod_Emittent>
        <Valuta>USD</Valuta>
        <Antal>16100</Antal>
        <Nominellt_belopp />
        <Kurs_som_använts_vid_värdering_av_instrumentet>230.14</Kurs_som_använts_vid_värdering_av_instrumentet>
        <Valutakurs_instrument>11.045</Valutakurs_instrument>
        <Marknadsvärde_instrument>40924530.43</Marknadsvärde_instrument>
        <Andel_av_fondförmögenhet_instrument>4.33</Andel_av_fondförmögenhet_instrument>
        <Bransch>
          <Branschkod_instrument>20</Branschkod_instrument>
          <Bransch_namn_instrument>Industrivaror och tjänster</Bransch_namn_instrument>
        </Bransch>
      </FinansielltInstrument>
      <FinansielltInstrument>
        <Tillgångsslag_enligt_LVF_5_kap>ÖverlåtbartVärdepapper</Tillgångsslag_enligt_LVF_5_kap>
        <Instrumentnamn>CBIZ INC</Instrumentnamn>
        <ISIN-kod_instrument>US1248051021</ISIN-kod_instrument>
        <Landkod_Emittent>US</Landkod_Emittent>
        <Valuta>USD</Valuta>
        <Antal>29400</Antal>
        <Nominellt_belopp />
        <Kurs_som_använts_vid_värdering_av_instrumentet>81.83</Kurs_som_använts_vid_värdering_av_instrumentet>
        <Valutakurs_instrument>11.045</Valutakurs_instrument>
        <Marknadsvärde_instrument>26572083.09</Marknadsvärde_instrument>
        <Andel_av_fondförmögenhet_instrument>2.81</Andel_av_fondförmögenhet_instrument>
        <Bransch>
          <Branschkod_instrument>20</Branschkod_instrument>
          <Bransch_namn_instrument>Industrivaror och tjänster</Bransch_namn_instrument>
        </Bransch>
      </FinansielltInstrument>
      <FinansielltInstrument>
        <Tillgångsslag_enligt_LVF_5_kap>ÖverlåtbartVärdepapper</Tillgångsslag_enligt_LVF_5_kap>
        <Instrumentnamn>API GROUP</Instrumentnamn>
        <ISIN-kod_instrument>US00187Y1001</ISIN-kod_instrument>
        <Landkod_Emittent>US</Landkod_Emittent>
        <Valuta>USD</Valuta>
        <Antal>62400</Antal>
        <Nominellt_belopp />
        <Kurs_som_använts_vid_värdering_av_instrumentet>35.97</Kurs_som_använts_vid_värdering_av_instrumentet>
        <Valutakurs_instrument>11.045</Valutakurs_instrument>
        <Marknadsvärde_instrument>24790811.76</Marknadsvärde_instrument>
        <Andel_av_fondförmögenhet_instrument>2.63</Andel_av_fondförmögenhet_instrument>
        <Bransch>
          <Branschkod_instrument>20</Branschkod_instrument>
          <Bransch_namn_instrument>Industrivaror och tjänster</Bransch_namn_instrument>
        </Bransch>
      </FinansielltInstrument>
      <FinansielltInstrument>
        <Tillgångsslag_enligt_LVF_5_kap>ÖverlåtbartVärdepapper</Tillgångsslag_enligt_LVF_5_kap>
        <Instrumentnamn>ADVANCED DRAINAGE</Instrumentnamn>
        <ISIN-kod_instrument>US00790R1041</ISIN-kod_instrument>
        <Landkod_Emittent>US</Landkod_Emittent>
        <Valuta>USD</Valuta>
        <Antal>12350</Antal>
        <Nominellt_belopp />
        <Kurs_som_använts_vid_värdering_av_instrumentet>115.6</Kurs_som_använts_vid_värdering_av_instrumentet>
        <Valutakurs_instrument>11.045</Valutakurs_instrument>
        <Marknadsvärde_instrument>15768504.7</Marknadsvärde_instrument>
        <Andel_av_fondförmögenhet_instrument>1.67</Andel_av_fondförmögenhet_instrument>
        <Bransch>
          <Branschkod_instrument>20</Branschkod_instrument>
          <Bransch_namn_instrument>Industrivaror och tjänster</Bransch_namn_instrument>
        </Bransch>
      </FinansielltInstrument>
      <FinansielltInstrument>
        <Tillgångsslag_enligt_LVF_5_kap>ÖverlåtbartVärdepapper</Tillgångsslag_enligt_LVF_5_kap>
        <Instrumentnamn>AXOS FINANCIAL</Instrumentnamn>
        <ISIN-kod_instrument>US05465C1009</ISIN-kod_instrument>
        <Landkod_Emittent>US</Landkod_Emittent>
        <Valuta>USD</Valuta>
        <Antal>53000</Antal>
        <Nominellt_belopp />
        <Kurs_som_använts_vid_värdering_av_instrumentet>69.85</Kurs_som_använts_vid_värdering_av_instrumentet>
        <Valutakurs_instrument>11.045</Valutakurs_instrument>
        <Marknadsvärde_instrument>40889142.25</Marknadsvärde_instrument>
        <Andel_av_fondförmögenhet_instrument>4.33</Andel_av_fondförmögenhet_instrument>
        <Bransch>
          <Branschkod_instrument>40</Branschkod_instrument>
          <Bransch_namn_instrument>Finans</Bransch_namn_instrument>
        </Bransch>
      </FinansielltInstrument>
      <FinansielltInstrument>
        <Tillgångsslag_enligt_LVF_5_kap>ÖverlåtbartVärdepapper</Tillgångsslag_enligt_LVF_5_kap>
        <Instrumentnamn>APPLIED IND TECHS</Instrumentnamn>
        <ISIN-kod_instrument>US03820C1053</ISIN-kod_instrument>
        <Landkod_Emittent>US</Landkod_Emittent>
        <Valuta>USD</Valuta>
        <Antal>8750</Antal>
        <Nominellt_belopp />
        <Kurs_som_använts_vid_värdering_av_instrumentet>239.47</Kurs_som_använts_vid_värdering_av_instrumentet>
        <Valutakurs_instrument>11.045</Valutakurs_instrument>
        <Marknadsvärde_instrument>23143278.81</Marknadsvärde_instrument>
        <Andel_av_fondförmögenhet_instrument>2.45</Andel_av_fondförmögenhet_instrument>
        <Bransch>
          <Branschkod_instrument>20</Branschkod_instrument>
          <Bransch_namn_instrument>Industrivaror och tjänster</Bransch_namn_instrument>
        </Bransch>
      </FinansielltInstrument>
      <FinansielltInstrument>
        <Tillgångsslag_enligt_LVF_5_kap>ÖverlåtbartVärdepapper</Tillgångsslag_enligt_LVF_5_kap>
        <Instrumentnamn>COMFORT SYSTEMS USA</Instrumentnamn>
        <ISIN-kod_instrument>US1999081045</ISIN-kod_instrument>
        <Landkod_Emittent>US</Landkod_Emittent>
        <Valuta>USD</Valuta>
        <Antal>9100</Antal>
        <Nominellt_belopp />
        <Kurs_som_använts_vid_värdering_av_instrumentet>424.06</Kurs_som_använts_vid_värdering_av_instrumentet>
        <Valutakurs_instrument>11.045</Valutakurs_instrument>
        <Marknadsvärde_instrument>42622058.57</Marknadsvärde_instrument>
        <Andel_av_fondförmögenhet_instrument>4.51</Andel_av_fondförmögenhet_instrument>
        <Bransch>
          <Branschkod_instrument>20</Branschkod_instrument>
          <Bransch_namn_instrument>Industrivaror och tjänster</Bransch_namn_instrument>
        </Bransch>
      </FinansielltInstrument>
      <FinansielltInstrument>
        <Tillgångsslag_enligt_LVF_5_kap>ÖverlåtbartVärdepapper</Tillgångsslag_enligt_LVF_5_kap>
        <Instrumentnamn>EURONEXT NV</Instrumentnamn>
        <ISIN-kod_instrument>NL0006294274</ISIN-kod_instrument>
        <Landkod_Emittent>NL</Landkod_Emittent>
        <Valuta>EUR</Valuta>
        <Antal>25000</Antal>
        <Nominellt_belopp />
        <Kurs_som_använts_vid_värdering_av_instrumentet>108.3</Kurs_som_använts_vid_värdering_av_instrumentet>
        <Valutakurs_instrument>11.4637</Valutakurs_instrument>
        <Marknadsvärde_instrument>31037967.75</Marknadsvärde_instrument>
        <Andel_av_fondförmögenhet_instrument>3.29</Andel_av_fondförmögenhet_instrument>
        <Bransch>
          <Branschkod_instrument>40</Branschkod_instrument>
          <Bransch_namn_instrument>Finans</Bransch_namn_instrument>
        </Bransch>
      </FinansielltInstrument>
      <FinansielltInstrument>
        <Tillgångsslag_enligt_LVF_5_kap>ÖverlåtbartVärdepapper</Tillgångsslag_enligt_LVF_5_kap>
        <Instrumentnamn>DIPLOMA</Instrumentnamn>
        <ISIN-kod_instrument>GB0001826634</ISIN-kod_instrument>
        <Landkod_Emittent>GB</Landkod_Emittent>
        <Valuta>GBP</Valuta>
        <Antal>65300</Antal>
        <Nominellt_belopp />
        <Kurs_som_använts_vid_värdering_av_instrumentet>42.5</Kurs_som_använts_vid_värdering_av_instrumentet>
        <Valutakurs_instrument>13.8199</Valutakurs_instrument>
        <Marknadsvärde_instrument>38353677.48</Marknadsvärde_instrument>
        <Andel_av_fondförmögenhet_instrument>4.06</Andel_av_fondförmögenhet_instrument>
        <Bransch>
          <Branschkod_instrument>20</Branschkod_instrument>
          <Bransch_namn_instrument>Industrivaror och tjänster</Bransch_namn_instrument>
        </Bransch>
      </FinansielltInstrument>
      <FinansielltInstrument>
        <Tillgångsslag_enligt_LVF_5_kap>ÖverlåtbartVärdepapper</Tillgångsslag_enligt_LVF_5_kap>
        <Instrumentnamn>FIRSTSERVICE CORP</Instrumentnamn>
        <ISIN-kod_instrument>CA33767E2024</ISIN-kod_instrument>
        <Landkod_Emittent>CA</Landkod_Emittent>
        <Valuta>CAD</Valuta>
        <Antal>11800</Antal>
        <Nominellt_belopp />
        <Kurs_som_använts_vid_värdering_av_instrumentet>260.39</Kurs_som_använts_vid_värdering_av_instrumentet>
        <Valutakurs_instrument>7.676</Valutakurs_instrument>
        <Marknadsvärde_instrument>23585292.95</Marknadsvärde_instrument>
        <Andel_av_fondförmögenhet_instrument>2.5</Andel_av_fondförmögenhet_instrument>
        <Bransch>
          <Branschkod_instrument>60</Branschkod_instrument>
          <Bransch_namn_instrument>Fastigheter</Bransch_namn_instrument>
        </Bransch>
      </FinansielltInstrument>
      <FinansielltInstrument>
        <Tillgångsslag_enligt_LVF_5_kap>ÖverlåtbartVärdepapper</Tillgångsslag_enligt_LVF_5_kap>
        <Instrumentnamn>EXCHANGE INCOME CORP</Instrumentnamn>
        <ISIN-kod_instrument>CA3012831077</ISIN-kod_instrument>
        <Landkod_Emittent>CA</Landkod_Emittent>
        <Valuta>CAD</Valuta>
        <Antal>43006</Antal>
        <Nominellt_belopp />
        <Kurs_som_använts_vid_värdering_av_instrumentet>58.85</Kurs_som_använts_vid_värdering_av_instrumentet>
        <Valutakurs_instrument>7.676</Valutakurs_instrument>
        <Marknadsvärde_instrument>19427212.2</Marknadsvärde_instrument>
        <Andel_av_fondförmögenhet_instrument>2.06</Andel_av_fondförmögenhet_instrument>
        <Bransch>
          <Branschkod_instrument>20</Branschkod_instrument>
          <Bransch_namn_instrument>Industrivaror och tjänster</Bransch_namn_instrument>
        </Bransch>
      </FinansielltInstrument>
      <FinansielltInstrument>
        <Tillgångsslag_enligt_LVF_5_kap>ÖverlåtbartVärdepapper</Tillgångsslag_enligt_LVF_5_kap>
        <Instrumentnamn>CYBERARK SOFTWARE LT</Instrumentnamn>
        <ISIN-kod_instrument>IL0011334468</ISIN-kod_instrument>
        <Landkod_Emittent>US</Landkod_Emittent>
        <Valuta>USD</Valuta>
        <Antal>9400</Antal>
        <Nominellt_belopp />
        <Kurs_som_använts_vid_värdering_av_instrumentet>333.15</Kurs_som_använts_vid_värdering_av_instrumentet>
        <Valutakurs_instrument>11.045</Valutakurs_instrument>
        <Marknadsvärde_instrument>34588632.45</Marknadsvärde_instrument>
        <Andel_av_fondförmögenhet_instrument>3.66</Andel_av_fondförmögenhet_instrument>
        <Bransch>
          <Branschkod_instrument>45</Branschkod_instrument>
          <Bransch_namn_instrument>Informationsteknologi</Bransch_namn_instrument>
        </Bransch>
      </FinansielltInstrument>
      <FinansielltInstrument>
        <Tillgångsslag_enligt_LVF_5_kap>ÖverlåtbartVärdepapper</Tillgångsslag_enligt_LVF_5_kap>
        <Instrumentnamn>CORE AND MAIN</Instrumentnamn>
        <ISIN-kod_instrument>US21874C1027</ISIN-kod_instrument>
        <Landkod_Emittent>US</Landkod_Emittent>
        <Valuta>USD</Valuta>
        <Antal>65300</Antal>
        <Nominellt_belopp />
        <Kurs_som_använts_vid_värdering_av_instrumentet>50.91</Kurs_som_använts_vid_värdering_av_instrumentet>
        <Valutakurs_instrument>11.045</Valutakurs_instrument>
        <Marknadsvärde_instrument>36718252.03</Marknadsvärde_instrument>
        <Andel_av_fondförmögenhet_instrument>3.89</Andel_av_fondförmögenhet_instrument>
        <Bransch>
          <Branschkod_instrument>20</Branschkod_instrument>
          <Bransch_namn_instrument>Industrivaror och tjänster</Bransch_namn_instrument>
        </Bransch>
      </FinansielltInstrument>
      <FinansielltInstrument>
        <Tillgångsslag_enligt_LVF_5_kap>ÖverlåtbartVärdepapper</Tillgångsslag_enligt_LVF_5_kap>
        <Instrumentnamn>DIGITALBRIDGE GROUP</Instrumentnamn>
        <ISIN-kod_instrument>US25401T6038</ISIN-kod_instrument>
        <Landkod_Emittent>US</Landkod_Emittent>
        <Valuta>USD</Valuta>
        <Antal>169500</Antal>
        <Nominellt_belopp />
        <Kurs_som_använts_vid_värdering_av_instrumentet>11.28</Kurs_som_använts_vid_värdering_av_instrumentet>
        <Valutakurs_instrument>11.045</Valutakurs_instrument>
        <Marknadsvärde_instrument>21117598.2</Marknadsvärde_instrument>
        <Andel_av_fondförmögenhet_instrument>2.24</Andel_av_fondförmögenhet_instrument>
        <Bransch>
          <Branschkod_instrument>40</Branschkod_instrument>
          <Bransch_namn_instrument>Finans</Bransch_namn_instrument>
        </Bransch>
      </FinansielltInstrument>
      <FinansielltInstrument>
        <Tillgångsslag_enligt_LVF_5_kap>ÖverlåtbartVärdepapper</Tillgångsslag_enligt_LVF_5_kap>
        <Instrumentnamn>DESCARTES SYSTEMS GR</Instrumentnamn>
        <ISIN-kod_instrument>CA2499061083</ISIN-kod_instrument>
        <Landkod_Emittent>CA</Landkod_Emittent>
        <Valuta>CAD</Valuta>
        <Antal>29400</Antal>
        <Nominellt_belopp />
        <Kurs_som_använts_vid_värdering_av_instrumentet>163.4</Kurs_som_använts_vid_värdering_av_instrumentet>
        <Valutakurs_instrument>7.676</Valutakurs_instrument>
        <Marknadsvärde_instrument>36875196.96</Marknadsvärde_instrument>
        <Andel_av_fondförmögenhet_instrument>3.91</Andel_av_fondförmögenhet_instrument>
        <Bransch>
          <Branschkod_instrument>45</Branschkod_instrument>
          <Bransch_namn_instrument>Informationsteknologi</Bransch_namn_instrument>
        </Bransch>
      </FinansielltInstrument>
    </FinansiellaInstrument>
  </Fondinformation>
  <Fondinformation />
</VärdepappersfondInnehav>